better_gsheets/colors.py
better_gsheets/conditionals.py
better_gsheets/deletion.py
better_gsheets/generation.py
better_gsheets/reading.py
better_gsheets-0.1.0.dist-info/licenses/LICENSE
better_gsheets-0.1.0.dist-info/METADATA
better_gsheets-0.1.0.dist-info/WHEEL
better_gsheets-0.1.0.dist-info/top_level.txt
better_gsheets-0.1.0.dist-info/RECORD
