Metadata-Version: 2.4
Name: better-gsheets
Version: 0.1.0
Summary: A higher-level, cleaner interface for the Google Sheets API.
Author-email: Zachary Richman <richmanzj@gmail.com>
License: MIT License
Project-URL: Homepage, https://github.com/Zachary-Richman/better-gsheets
Project-URL: Repository, https://github.com/Zachary-Richman/better-gsheets
Project-URL: Issues, https://github.com/Zachary-Richman/better-gsheets/issues
Requires-Python: >=3.8
License-File: LICENSE
Requires-Dist: google-api-python-client
Requires-Dist: google-auth
Requires-Dist: google-auth-oauthlib
Dynamic: license-file
